hyper_bump_it/__init__.py
hyper_bump_it/__main__.py
hyper_bump_it/py.typed
hyper_bump_it/_hyper_bump_it/compat.py
hyper_bump_it/_hyper_bump_it/core.py
hyper_bump_it/_hyper_bump_it/error.py
hyper_bump_it/_hyper_bump_it/execution_plan.py
hyper_bump_it/_hyper_bump_it/files.py
hyper_bump_it/_hyper_bump_it/planned_changes.py
hyper_bump_it/_hyper_bump_it/ui.py
hyper_bump_it/_hyper_bump_it/vcs.py
hyper_bump_it/_hyper_bump_it/version.py
hyper_bump_it/_hyper_bump_it/cli/__init__.py
hyper_bump_it/_hyper_bump_it/cli/by.py
hyper_bump_it/_hyper_bump_it/cli/common.py
hyper_bump_it/_hyper_bump_it/cli/init.py
hyper_bump_it/_hyper_bump_it/cli/to.py
hyper_bump_it/_hyper_bump_it/cli/interactive/__init__.py
hyper_bump_it/_hyper_bump_it/cli/interactive/file_validation.py
hyper_bump_it/_hyper_bump_it/cli/interactive/files.py
hyper_bump_it/_hyper_bump_it/cli/interactive/git.py
hyper_bump_it/_hyper_bump_it/cli/interactive/top_level.py
hyper_bump_it/_hyper_bump_it/config/__init__.py
hyper_bump_it/_hyper_bump_it/config/application.py
hyper_bump_it/_hyper_bump_it/config/cli.py
hyper_bump_it/_hyper_bump_it/config/core.py
hyper_bump_it/_hyper_bump_it/config/file.py
hyper_bump_it/_hyper_bump_it/config/keystone_parser.py
hyper_bump_it/_hyper_bump_it/format_pattern/__init__.py
hyper_bump_it/_hyper_bump_it/format_pattern/keys.py
hyper_bump_it/_hyper_bump_it/format_pattern/matching_pattern.py
hyper_bump_it/_hyper_bump_it/format_pattern/text_formatter.py
hyper_bump_it-0.5.3.dist-info/METADATA
hyper_bump_it-0.5.3.dist-info/WHEEL
hyper_bump_it-0.5.3.dist-info/entry_points.txt
hyper_bump_it-0.5.3.dist-info/licenses/LICENSE
hyper_bump_it-0.5.3.dist-info/RECORD
