Metadata-Version: 2.3
Name: hyper-bump-it
Version: 0.5.3
Summary: A version bumping tool
Project-URL: homepage, https://github.com/plannigan/hyper-bump-it
Project-URL: changelog, https://github.com/plannigan/hyper-bump-it/blob/main/CHANGELOG.md
Project-URL: issues, https://github.com/plannigan/hyper-bump-it/issues
Project-URL: documentation, https://plannigan.github.io/hyper-bump-it
Author-email: Patrick Lannigan <p.lannigan@gmail.com>
License: MIT
License-File: LICENSE
Keywords: bump,command line,version
Classifier: Development Status :: 4 - Beta
Classifier: License :: OSI Approved :: MIT License
Classifier: Programming Language :: Python :: 3
Classifier: Programming Language :: Python :: 3.9
Classifier: Programming Language :: Python :: 3.10
Classifier: Programming Language :: Python :: 3.11
Classifier: Programming Language :: Python :: 3.12
Requires-Python: <4.0,>=3.9
Requires-Dist: gitpython<4,>=3.1.35
Requires-Dist: pydantic<3,>=2.1.0
Requires-Dist: rich<14,>=12.6.0
Requires-Dist: tomlkit<1.0,>=0.11.6
Requires-Dist: typer<1.0,>=0.9.0
Requires-Dist: typing-extensions<5,>=4.4.0; python_version < '3.11'
